pangbank_cli/__init__.py
pangbank_cli/collections.py
pangbank_cli/main.py
pangbank_cli/match_pangenome.py
pangbank_cli/pangenomes.py
pangbank_cli/utils.py
pangbank_cli-0.1.1.dist-info/licenses/LICENCE
pangbank_cli-0.1.1.dist-info/METADATA
pangbank_cli-0.1.1.dist-info/WHEEL
pangbank_cli-0.1.1.dist-info/entry_points.txt
pangbank_cli-0.1.1.dist-info/top_level.txt
pangbank_cli-0.1.1.dist-info/RECORD
