Metadata-Version: 2.4
Name: PanGBank-cli
Version: 0.1.1
Summary: Command-line tool for retrieving pangenomes using the PanGBank API. 
Author: Jean Mainguy
Maintainer: Jean Mainguy
License: 
Project-URL: Repository, https://github.com/labgem/PanGBank-cli
Project-URL: Changelog, https://github.com/labgem/PanGBank-cli/CHANGELOG.md
Keywords: Bioinformatics,Prokaryotes,Genomics,Pangenome,comparative-genomics,database,API
Classifier: Environment :: Console
Classifier: Intended Audience :: Science/Research
Classifier: License :: OSI Approved :: MIT License
Classifier: Natural Language :: English
Classifier: Operating System :: POSIX :: Linux
Classifier: Programming Language :: Python :: 3.10
Classifier: Programming Language :: Python :: 3.11
Classifier: Programming Language :: Python :: 3.12
Classifier: Programming Language :: Python :: 3.13
Classifier: Topic :: Scientific/Engineering :: Bio-Informatics
Classifier: Typing :: Typed
Requires-Python: <3.14,>=3.10
License-File: LICENCE
Requires-Dist: typer>=0.15.1
Requires-Dist: requests>=2.32.3
Requires-Dist: rich>=10.0.0
Requires-Dist: pydantic<3.0.0,>=2.10.0
Requires-Dist: pandas<3.0.0,>=2.0.0
Requires-Dist: pangbank-api>=0.1.1
Provides-Extra: dev
Requires-Dist: pytest>=8.0.0; extra == "dev"
Requires-Dist: pytest-cov; extra == "dev"
Requires-Dist: black>=8.0.0; extra == "dev"
Dynamic: license-file
